[{"crime": "assault", "id": "03xb2BUdIFzuRQ6o88yfCB"}, {"crime": "sexual misconduct", "id": "7gZfnEnfiaHzxARJ2LeXrf"}, {"crime": "assault occasioning actual bodily harm", "id": "3NyNPJaemMYsL14DK2tO01"}, {"crime": "driving under the influence", "id": "4yBK75WVCQXej1p04GWqxH"}, {"crime": "voluntary manslaughter", "id": "5r0O4LLn9wHEuYxKmGzUB5"}, {"crime": "battery", "id": "4GMgdB3vwbBOc42hbXEi9p"}, {"crime": "tax noncompliance", "id": "3LIJJJkO7R5RasRwt7xIn5"}, {"crime": "tax noncompliance", "id": "7JmZ8ZiTfj42TZIbVFP7YD"}, {"crime": "theft", "id": "504cl42JQLRqlZddfZ3S4z"}, {"crime": "deliberate murder", "id": "3J1JmDJt3pJ6BCtmNk4HOz"}, {"crime": "fraud", "id": "6ynopZPMBXcIGBI9M02Un5"}, {"crime": "vehicular homicide", "id": "1CF7hrTuWgErEa6HBFJ8d3"}, {"crime": "possession of a controlled substance", "id": "20sxb77xiYeusSH8cVdatc"}, {"crime": "possession of a controlled substance", "id": "0VRj0yCOv2FXJNP47XQnx5"}, {"crime": "assault", "id": "7GaxyUddsPok8BuhxN6OUW"}, {"crime": "robbery", "id": "6XFQvBHGEr3mRfOHcqPXv8"}, {"crime": "drug trafficking", "id": "1fux65HMCBvfJHqlBc4Nno"}, {"crime": "second-degree murder", "id": "3J1JmDJt3pJ6BCtmNk4HOz"}, {"crime": "conspiracy to murder", "id": "7gZfnEnfiaHzxARJ2LeXrf"}, {"crime": "statutory rape", "id": "2mxe0TnaNL039ysAj51xPQ"}, {"crime": "possession of a controlled substance", "id": "336vr2M3Va0FjyvB55lJEd"}, {"crime": "vandalism", "id": "24RkW6OmQCTvgvwZM89nMG"}, {"crime": "firearm", "id": "5F1aAS1duwlzExnPs3l2Xe"}, {"crime": "assault", "id": "50NoVNy9GU1lCrDV8iGpyu"}, {"crime": "cannabis smoking", "id": "1anyVhU62p31KFi8MEzkbf"}, {"crime": "calumny", "id": "5W3MomKhcR7lP7PVStCY5h"}, {"crime": "violence", "id": "59WNMskn4tSvgnWKXHXj61"}, {"crime": "assault", "id": "2MEWgRS9kjwxFXxbFBTnPO"}, {"crime": "driving under the influence", "id": "3jksrX4oBklxR78ft8gv3j"}, {"crime": "Q1228732", "id": "4VuARVJiWGsH2msKTdsKdQ"}, {"crime": "insurance fraud", "id": "3c96G4d2lUOxhomM2mby5S"}, {"crime": "possession of a controlled substance", "id": "571DQ56F4RZTd4Fy2Tn2ZR"}, {"crime": "criminal possession of a weapon", "id": "4yBK75WVCQXej1p04GWqxH"}, {"crime": "murder", "id": "2ODbg2404zUzTi02qIPEjB"}, {"crime": "murder", "id": "7f35VZGDpomj11PXdNn5D9"}, {"crime": "possession of a controlled substance", "id": "0WfKB7Lqqykt6gdtirYJUm"}, {"crime": "Q2660205", "id": "3c96G4d2lUOxhomM2mby5S"}, {"crime": "manslaughter", "id": "3mOiEPe870jJrahcf2TPYZ"}, {"crime": "assault", "id": "0FrpdcVlJQqibaz5HfBUrL"}, {"crime": "battery", "id": "6DPYiyq5kWVQS4RGwxzPC7"}, {"crime": "assault", "id": "3YBIrJozn8fop4UYIt7wcV"}, {"crime": "Steuerhinterziehung", "id": "3c96G4d2lUOxhomM2mby5S"}, {"crime": "kidnapping", "id": "7f35VZGDpomj11PXdNn5D9"}, {"crime": "murder", "id": "1ALiu7S9gPJPSw122Ds1t2"}, {"crime": "robbery", "id": "2Q2fYVYxFSmodq53BFyD6p"}, {"crime": "robbery", "id": "4AADwRHHIeyMQxnB0KPcSS"}, {"crime": "battery", "id": "4yBK75WVCQXej1p04GWqxH"}, {"crime": "driving under the influence", "id": "336vr2M3Va0FjyvB55lJEd"}, {"crime": "possession of a controlled substance", "id": "1vkJFCwstOoJO7yQ4lTtLK"}, {"crime": "sodomy", "id": "0xGP8NSgSqh0dSbtx6S8HL"}, {"crime": "sodomy", "id": "2fyX3KN0QchIB4mRmwKbzn"}, {"crime": "assault", "id": "1W9qOBYRTfP7HcizWN43G1"}, {"crime": "assault", "id": "1ZwdS5xdxEREPySFridCfh"}, {"crime": "criminal possession of a weapon", "id": "3jksrX4oBklxR78ft8gv3j"}, {"crime": "murder", "id": "2l1WElL3bl1lKH05n0gYLa"}, {"crime": "assault", "id": "0b2XeWDPeBiLeskT6RFqMb"}, {"crime": "fraud", "id": "6oGu0NZWy8gJ18wggybFqH"}, {"crime": "making false statements", "id": "46SHBwWsqBkxI7EeeBEQG7"}, {"crime": "rape", "id": "5MCgysjFa88X9uVFMKHbDe"}, {"crime": "criminal possession of a weapon", "id": "20sxb77xiYeusSH8cVdatc"}, {"crime": "racket", "id": "7gZfnEnfiaHzxARJ2LeXrf"}, {"crime": "attempted murder", "id": "3Ovf2lytXSXWFM2cwsJACC"}, {"crime": "battery", "id": "6cEgg5LusRPDempyGkrOBH"}, {"crime": "assault", "id": "3nFkdlSjzX9mRTtwJOzDYB"}, {"crime": "armed robbery", "id": "7gZfnEnfiaHzxARJ2LeXrf"}, {"crime": "manslaughter", "id": "08oMhAUN23C91R1zltrR6p"}, {"crime": "driving under the influence", "id": "1vkJFCwstOoJO7yQ4lTtLK"}, {"crime": "attempted second-degree murder", "id": "3J1JmDJt3pJ6BCtmNk4HOz"}, {"crime": "theft", "id": "1HwM5zlC5qNWhJtM00yXzG"}, {"crime": "assault", "id": "1cNDP5yjU5vjeR8qMf4grg"}, {"crime": "theft", "id": "571DQ56F4RZTd4Fy2Tn2ZR"}, {"crime": "assault", "id": "4IKQKM9T5OIshijgLD8ZyK"}, {"crime": "demonstration", "id": "4tO30StPjWGPaJnkNzVX3T"}, {"crime": "assault", "id": "1wvlC6NwleHt1iRD6d5X2C"}, {"crime": "excessive speed", "id": "6DPYiyq5kWVQS4RGwxzPC7"}, {"crime": "assault", "id": "2jku7tDXc6XoB6MO2hFuqg"}, {"crime": "assault", "id": "4OBJLual30L7gRl5UkeRcT"}, {"crime": "child sexual abuse", "id": "61zv3hX7l838ZyhaDyAx8S"}, {"crime": "motor vehicle theft", "id": "15iVAtD3s3FsQR4w1v6M0P"}, {"crime": "murder", "id": "2NUz5P42WqkxilbI8ocN76"}, {"crime": "copyright infringement", "id": "4yBK75WVCQXej1p04GWqxH"}, {"crime": "sex trafficking", "id": "2mxe0TnaNL039ysAj51xPQ"}, {"crime": "gross indecency", "id": "44HAGCeIkbH5fuVDy4SkoQ"}, {"crime": "murder", "id": "7HtxMkp03oA3C1d8KzImnm"}, {"crime": "demonstration", "id": "4O8DQCEBU9I1wQ274THitE"}, {"crime": "trespass", "id": "571DQ56F4RZTd4Fy2Tn2ZR"}, {"crime": "political activity", "id": "6tUIot9mdCbKUGpBZTJKG2"}, {"crime": "political activity", "id": "3cRrVfyF5xRO3EQQklAtWp"}, {"crime": "assault", "id": "20sxb77xiYeusSH8cVdatc"}, {"crime": "driving under the influence", "id": "2OFEXARoSZyZLR6S0oV2R7"}, {"crime": "reckless driving", "id": "15iVAtD3s3FsQR4w1v6M0P"}, {"crime": "assault", "id": "0DchahWJGQqrqr8PMM5zQD"}, {"crime": "drug trafficking", "id": "7gZfnEnfiaHzxARJ2LeXrf"}, {"crime": "tax noncompliance", "id": "293zczrfYafIItmnmM3coR"}, {"crime": "Article 299 (Turkish Penal Code)", "id": "6XTIDpYqIA3fUeQM8zA4Ix"}, {"crime": "assault", "id": "2I1bnmb9VQEQGKHxvr0gSf"}, {"crime": "bodily harm", "id": "7jDSMakHqXFe8kIaXfz8jD"}, {"crime": "assault", "id": "1YfEcTuGvBQ8xSD1f53UnK"}, {"crime": "manslaughter", "id": "0lnmOlfPfbxcsUOOhO3Rgo"}, {"crime": "manslaughter", "id": "1jygJqFtCbFeOPv4w0NViD"}, {"crime": "manslaughter", "id": "63JKrVhkZC6euXEFnZii8e"}, {"crime": "false imprisonment", "id": "4yBK75WVCQXej1p04GWqxH"}, {"crime": "Q1228732", "id": "6XFQvBHGEr3mRfOHcqPXv8"}, {"crime": "copyright infringement", "id": "3c96G4d2lUOxhomM2mby5S"}, {"crime": "assault", "id": "320OQx68FlvfJiPGSx5mxW"}, {"crime": "indecent assault", "id": "61zv3hX7l838ZyhaDyAx8S"}, {"crime": "child sexual abuse", "id": "7jDSMakHqXFe8kIaXfz8jD"}, {"crime": "stabbing", "id": "4oplcYQTrcAtwy7iamWHkC"}, {"crime": "fraud", "id": "71VUe3HlEyivVpoIel6TpE"}, {"crime": "drug trafficking", "id": "571DQ56F4RZTd4Fy2Tn2ZR"}, {"crime": "murder", "id": "3L8e5UKusJgynEkrT60rlT"}, {"crime": "contract killing", "id": "0m3Y5xx8JYQT0y1cFZyd7z"}, {"crime": "terroristic threat", "id": "4yBK75WVCQXej1p04GWqxH"}, {"crime": "second-degree murder", "id": "3jVMgT4X7YeuYE4aludcmE"}, {"crime": "robbery", "id": "13y7CgLHjMVRMDqxdx0Xdo"}, {"crime": "threat", "id": "2Q2fYVYxFSmodq53BFyD6p"}, {"crime": "threat", "id": "4AADwRHHIeyMQxnB0KPcSS"}, {"crime": "sexual abuse", "id": "1ZwdS5xdxEREPySFridCfh"}, {"crime": "driving under the influence", "id": "1cGAI8rl33xtRQW12YsnTq"}, {"crime": "robbery", "id": "7GaxyUddsPok8BuhxN6OUW"}, {"crime": "robbery", "id": "7f35VZGDpomj11PXdNn5D9"}, {"crime": "child sexual abuse", "id": "4kKaAWGdu6WW0W415RWaQA"}, {"crime": "manslaughter", "id": "2OFEXARoSZyZLR6S0oV2R7"}, {"crime": "assault", "id": "5MCgysjFa88X9uVFMKHbDe"}, {"crime": "aggravated robbery", "id": "571DQ56F4RZTd4Fy2Tn2ZR"}, {"crime": "child pornography", "id": "61zv3hX7l838ZyhaDyAx8S"}, {"crime": "cruelty to animals", "id": "0m3Y5xx8JYQT0y1cFZyd7z"}, {"crime": "murder", "id": "3Ovf2lytXSXWFM2cwsJACC"}, {"crime": "conspiracy to commit a crime", "id": "5F1aAS1duwlzExnPs3l2Xe"}, {"crime": "assault", "id": "7v9bFXCdSMA2o3gS4nvp0F"}, {"crime": "demonstration", "id": "5EvLD8ZqQKUQVTORi5z8tm"}, {"crime": "tax noncompliance", "id": "1J2VVASYAamtQ3Bt8wGgA6"}, {"crime": "disorderly conduct", "id": "7gZfnEnfiaHzxARJ2LeXrf"}, {"crime": "racket", "id": "2mxe0TnaNL039ysAj51xPQ"}, {"crime": "assault", "id": "36ikBJX6oQWWlgrXCock30"}, {"crime": "fraud", "id": "1ddbFlSqbqp2vuJd5CuRcE"}, {"crime": "Steuerhinterziehung", "id": "7jDSMakHqXFe8kIaXfz8jD"}, {"crime": "assault", "id": "5mNB8ykTlENptzmsxXRtdS"}]